<?xml version="1.0" encoding="utf-8" ?>
<dwsync>
<file name="navg.php" server="ec2-18-117-218-14.us-east-2.compute.amazonaws.com//var/www/html/" local="132960219809023214" remote="132960220520000000" Dst="2" />
<file name="contact.php" server="ec2-18-117-218-14.us-east-2.compute.amazonaws.com//var/www/html/" local="132960180162368643" remote="132960186720000000" Dst="2" />
<file name="entries.php" server="ec2-18-117-218-14.us-east-2.compute.amazonaws.com//var/www/html/" local="132960211019052656" remote="132960211150000000" Dst="2" />
<file name="function.php" server="ec2-18-117-218-14.us-east-2.compute.amazonaws.com//var/www/html/" local="132954778554181025" remote="132960186720000000" Dst="2" />
<file name="home.php" server="ec2-18-117-218-14.us-east-2.compute.amazonaws.com//var/www/html/" local="132960193786984579" remote="132960193860000000" Dst="2" />
<file name="index.php" server="ec2-18-117-218-14.us-east-2.compute.amazonaws.com//var/www/html/" local="132960220950000000" remote="132960220950000000" Dst="2" />
<file name="query_entries.php" server="ec2-18-117-218-14.us-east-2.compute.amazonaws.com//var/www/html/" local="132958459992462135" remote="132960186750000000" Dst="2" />
<file name="school.php" server="ec2-18-117-218-14.us-east-2.compute.amazonaws.com//var/www/html/" local="132960194221206787" remote="132960194410000000" Dst="2" />
<file name="work.php" server="ec2-18-117-218-14.us-east-2.compute.amazonaws.com//var/www/html/" local="132960194326263676" remote="132960194420000000" Dst="2" />
</dwsync>